db_handler/__init__.py
db_handler-0.2.0.dist-info/METADATA
db_handler-0.2.0.dist-info/WHEEL
db_handler-0.2.0.dist-info/RECORD
